{
  "name": "企业会计准则审计检查清单",
  "items": [
    {
      "category": "资产类",
      "checks": [
        "应收账款账龄分析是否合理",
        "坏账准备计提是否充分（预期信用损失模型）",
        "存货是否进行跌价测试",
        "固定资产是否存在减值迹象",
        "无形资产摊销政策是否合理",
        "长期股权投资核算方法是否正确（成本法/权益法）"
      ]
    },
    {
      "category": "负债类",
      "checks": [
        "或有负债是否充分披露",
        "预计负债确认是否合理",
        "长期借款利息是否正确计提",
        "递延所得税负债是否完整确认"
      ]
    },
    {
      "category": "损益类",
      "checks": [
        "收入确认时点是否符合准则（五步法）",
        "费用归属期间是否正确",
        "资产减值损失计提是否充分",
        "所得税费用（当期+递延）计算是否正确"
      ]
    },
    {
      "category": "披露",
      "checks": [
        "关联方关系及交易是否完整披露",
        "重大会计估计和判断是否说明",
        "或有事项是否披露",
        "资产负债表日后事项是否处理"
      ]
    }
  ]
}
